azureml/__init__.py
azureml/fsspec/__init__.py
azureml/fsspec/spec.py
azureml/fsspec/tests/__init__.py
azureml/fsspec/tests/conftest.py
azureml/fsspec/tests/test_fsspec.py
azureml_fsspec-1.3.1.dist-info/LICENSE.txt
azureml_fsspec-1.3.1.dist-info/METADATA
azureml_fsspec-1.3.1.dist-info/WHEEL
azureml_fsspec-1.3.1.dist-info/entry_points.txt
azureml_fsspec-1.3.1.dist-info/top_level.txt
azureml_fsspec-1.3.1.dist-info/RECORD
