Metadata-Version: 2.1
Name: azureml-fsspec
Version: 1.3.1
Summary: Access datastore uri with fsspec
Home-page: https://docs.microsoft.com/python/api/overview/azure/ml/?view=azure-ml-py
Author: Microsoft Corp
License: Proprietary https://aka.ms/azureml-preview-sdk-license 
Keywords: file-system,dask,azure
Classifier: Development Status :: 5 - Production/Stable
Classifier: Intended Audience :: Developers
Classifier: Intended Audience :: Science/Research
Classifier: License :: Other/Proprietary License
Classifier: Programming Language :: Python :: 3.7
Classifier: Programming Language :: Python :: 3.8
Classifier: Programming Language :: Python :: 3.9
Classifier: Programming Language :: Python :: 3.10
Classifier: Programming Language :: Python :: 3.11
Classifier: Operating System :: MacOS
Classifier: Operating System :: Microsoft :: Windows
Classifier: Operating System :: POSIX :: Linux
Classifier: Topic :: Scientific/Engineering
Requires-Python: >=3.6,< 4.0
License-File: LICENSE.txt
Requires-Dist: azureml-dataprep <5.2.0a,>=5.1.0a
Requires-Dist: fsspec <=2023.10.0,>=2021.6.1
Requires-Dist: pytz
